alphafold/__init__.py
alphafold/common/__init__.py
alphafold/common/confidence.py
alphafold/common/protein.py
alphafold/common/protein_test.py
alphafold/common/residue_constants.py
alphafold/common/residue_constants_test.py
alphafold/data/__init__.py
alphafold/data/mmcif_parsing.py
alphafold/data/parsers.py
alphafold/data/pipeline.py
alphafold/data/templates.py
alphafold/model/__init__.py
alphafold/model/all_atom.py
alphafold/model/all_atom_test.py
alphafold/model/common_modules.py
alphafold/model/config.py
alphafold/model/data.py
alphafold/model/features.py
alphafold/model/folding.py
alphafold/model/layer_stack.py
alphafold/model/layer_stack_test.py
alphafold/model/lddt.py
alphafold/model/lddt_test.py
alphafold/model/mapping.py
alphafold/model/model.py
alphafold/model/modules.py
alphafold/model/prng.py
alphafold/model/prng_test.py
alphafold/model/quat_affine.py
alphafold/model/quat_affine_test.py
alphafold/model/r3.py
alphafold/model/utils.py
alphafold/relax/__init__.py
alphafold/relax/amber_minimize.py
alphafold/relax/amber_minimize_test.py
alphafold/relax/cleanup.py
alphafold/relax/cleanup_test.py
alphafold/relax/relax.py
alphafold/relax/relax_test.py
alphafold/relax/utils.py
alphafold/relax/utils_test.py
alphafold-2.0.0.dist-info/LICENSE
alphafold-2.0.0.dist-info/METADATA
alphafold-2.0.0.dist-info/WHEEL
alphafold-2.0.0.dist-info/top_level.txt
alphafold-2.0.0.dist-info/RECORD
