Metadata-Version: 2.1
Name: alphafold
Version: 2.0.0
Summary: An implementation of the inference pipeline of AlphaFold v2.0.This is a completely new model that was entered as AlphaFold2 in CASP14 and published in Nature.
Home-page: https://github.com/deepmind/alphafold
Author: DeepMind
Author-email: alphafold@deepmind.com
License: Apache License, Version 2.0
Platform: UNKNOWN
Classifier: Development Status :: 5 - Production/Stable
Classifier: Intended Audience :: Science/Research
Classifier: License :: OSI Approved :: Apache Software License
Classifier: Operating System :: POSIX :: Linux
Classifier: Programming Language :: Python :: 3.6
Classifier: Programming Language :: Python :: 3.7
Classifier: Topic :: Scientific/Engineering :: Artificial Intelligence
License-File: LICENSE
Requires-Dist: absl-py
Requires-Dist: biopython
Requires-Dist: chex
Requires-Dist: dm-haiku
Requires-Dist: dm-tree
Requires-Dist: docker
Requires-Dist: immutabledict
Requires-Dist: jax
Requires-Dist: ml-collections
Requires-Dist: numpy
Requires-Dist: scipy
Requires-Dist: tensorflow
